thermoworks_cloud/__init__.py
thermoworks_cloud/auth.py
thermoworks_cloud/core.py
thermoworks_cloud/utils.py
thermoworks_cloud/models/__init__.py
thermoworks_cloud/models/device.py
thermoworks_cloud/models/device_channel.py
thermoworks_cloud/models/user.py
thermoworks_cloud/models/user_credentials.py
thermoworks_cloud-0.1.11.dist-info/licenses/LICENSE.txt
thermoworks_cloud-0.1.11.dist-info/METADATA
thermoworks_cloud-0.1.11.dist-info/WHEEL
thermoworks_cloud-0.1.11.dist-info/top_level.txt
thermoworks_cloud-0.1.11.dist-info/RECORD
