Metadata-Version: 2.4
Name: thermoworks-cloud
Version: 0.1.11
Summary: Pull data for Thermoworks Cloud enabled thermometers
Author-email: Austin Hill <austin@nitsua.org>
License:                     GNU GENERAL PUBLIC LICENSE
Project-URL: GitHub, https://github.com/a2hill/python-thermoworks-cloud
Keywords: thermometer,ThermoWorks,ThermoWorks Cloud,NODE
Classifier: Development Status :: 3 - Alpha
Classifier: Intended Audience :: Developers
Classifier: License :: OSI Approved :: GNU General Public License v3 (GPLv3)
Classifier: Programming Language :: Python :: 3.10
Requires-Python: >=3.10
License-File: LICENSE.txt
Requires-Dist: aiohttp>=3.11.7
Provides-Extra: dev
Requires-Dist: black>=24.8.0; extra == "dev"
Requires-Dist: pytest>=8.3.4; extra == "dev"
Requires-Dist: pytest-asyncio>=0.25.0; extra == "dev"
Requires-Dist: aioresponses>=0.7.7; extra == "dev"
Requires-Dist: pytest_httpserver>=1.1.0; extra == "dev"
Requires-Dist: pytest-cov>=6.0.0; extra == "dev"
Requires-Dist: pylint>=3.3.0; extra == "dev"
Requires-Dist: pdoc>=15.0.1; extra == "dev"
Dynamic: license-file
